geoparquet/__init__.py
geoparquet-0.0.3.dist-info/LICENSE.txt
geoparquet-0.0.3.dist-info/METADATA
geoparquet-0.0.3.dist-info/WHEEL
geoparquet-0.0.3.dist-info/top_level.txt
geoparquet-0.0.3.dist-info/RECORD
