Metadata-Version: 2.1
Name: geoparquet
Version: 0.0.3
Summary: GeoPandas API for Parquet file format.
Home-page: https://github.com/darcy-r/geoparquet-python
Author: D'Arcy Roche
Author-email: d.arcy@posteo.de
License: UNKNOWN
Platform: UNKNOWN
Classifier: Programming Language :: Python :: 3
Classifier: License :: OSI Approved :: MIT License
Classifier: Operating System :: OS Independent
Classifier: Topic :: Scientific/Engineering :: GIS
